Metadata-Version: 2.1
Name: dyn-libs
Version: 0.2.3
Summary: Mobio Dynamic Fields
Home-page: https://github.com/mobiovn
Author: MOBIO
Author-email: contact@mobio.vn
License: MIT
Platform: UNKNOWN
Classifier: Topic :: Software Development
Classifier: Development Status :: 4 - Beta
Classifier: Intended Audience :: Developers
Classifier: License :: OSI Approved :: MIT License
Classifier: Programming Language :: Python :: 3
Classifier: Programming Language :: Python :: 3.4
Classifier: Programming Language :: Python :: 3.5
Classifier: Programming Language :: Python :: 3.6
Classifier: Programming Language :: Python :: 3.7
Classifier: Programming Language :: Python :: 3.8
Classifier: Programming Language :: Python :: 3.9
Classifier: Programming Language :: Python :: Implementation :: CPython
Classifier: Programming Language :: Python :: Implementation :: PyPy
Requires-Dist: m-singleton (==0.3)
Requires-Dist: pymongo (==3.7.2)
Requires-Dist: requests (==2.25.1)
Requires-Dist: unidecode (==1.1.1)
Requires-Dist: elasticsearch (<6.0.0,>=5.0.0)
